LICENSE
MANIFEST.in
README.md
setup.cfg
setup.py
click_completion/__init__.py
click_completion/bash.j2
click_completion/fish.j2
click_completion/powershell.j2
click_completion/zsh.j2
click_completion.egg-info/PKG-INFO
click_completion.egg-info/SOURCES.txt
click_completion.egg-info/dependency_links.txt
click_completion.egg-info/requires.txt
click_completion.egg-info/top_level.txt