Metadata-Version: 1.0
Name: click-completion
Version: 0.3.1
Summary: Fish, Bash, Zsh and PowerShell completion for Click
Home-page: https://github.com/click-contrib/click-completion
Author: Gaëtan Lehmann
Author-email: gaetan.lehmann@gmail.com
License: MIT
Platform: UNKNOWN
